[
  {
    "PackageName": "Weikio.PluginFramework",
    "PackageVersion": "1.5.1",
    "LicenseType ": "MIT",
    "LicenseUrl": "https://raw.githubusercontent.com/weikio/PluginFramework/master/LICENSE"
  },
  {
    "PackageName": "Weikio.PluginFramework.Abstractions",
    "PackageVersion": "1.5.1",
    "LicenseType ": "MIT",
    "LicenseUrl": "https://raw.githubusercontent.com/weikio/PluginFramework/master/LICENSE"
  },
  {
    "PackageName": "Weikio.PluginFramework.AspNetCore",
    "PackageVersion": "1.5.1",
    "LicenseType ": "MIT",
    "LicenseUrl": "https://raw.githubusercontent.com/weikio/PluginFramework/master/LICENSE"
  },
  {
    "PackageName": "Weikio.PluginFramework.Configuration",
    "PackageVersion": "1.5.1",
    "LicenseType ": "MIT",
    "LicenseUrl": "https://raw.githubusercontent.com/weikio/PluginFramework/master/LICENSE"
  },
  {
    "PackageName": "Microsoft-WindowsAPICodePack-Core",
    "PackageVersion": "1.1.4",
    "LicenseUrl": "https://raw.githubusercontent.com/contre/Windows-API-Code-Pack-1.1/master/LICENSE"
  },
  {
    "PackageName": "Microsoft-WindowsAPICodePack-Shell",
    "PackageVersion": "1.1.4",
    "LicenseUrl": "https://raw.githubusercontent.com/contre/Windows-API-Code-Pack-1.1/master/LICENSE"
  }
]
